{
  "data": [
    {
      "coinId": 35701,
      "auditor": "Verichains",
      "auditStatus": 2,
      "reportUrl": "https://verichains.io/?search=gohome"
    },
    {
      "coinId": 34420,
      "auditor": "Verichains",
      "auditStatus": 2,
      "reportUrl": "https://verichains.io/?search=pentagon"
    },
    {
      "coinId": 34053,
      "auditor": "Verichains",
      "auditStatus": 2,
      "reportUrl": "https://verichains.io/?search=develad"
    },
    {
      "coinId": 23147,
      "auditor": "Verichains",
      "auditStatus": 2,
      "reportUrl": "https://www.verichains.io/?search=shopnext"
    },
    {
      "coinId": 14892,
      "auditor": "Verichains",
      "auditStatus": 2,
      "reportUrl": "https://www.verichains.io/?search=koakuma"
    },
    {
      "coinId": 20330,
      "auditor": "Verichains",
      "auditStatus": 2,
      "reportUrl": "https://verichains.io?search=runnow"
    },
    {
      "coinId": 22811,
      "auditor": "Verichains",
      "auditStatus": 2,
      "reportUrl": "https://verichains.io?search=proton+sale"
    },
    {
      "coinId": 13769,
      "auditor": "Verichains",
      "auditStatus": 2,
      "reportUrl": "https://www.verichains.io/?search=world+mobile+token"
    },
    {
      "coinId": 9263,
      "auditor": "Verichains",
      "auditStatus": 2,
      "reportUrl": "https://www.verichains.io/?search=unizen"
    },
    {
      "coinId": 23148,
      "auditor": "Verichains",
      "auditStatus": 2,
      "reportUrl": "https://www.verichains.io/?search=shopnext"
    },
    {
      "coinId": 2570,
      "auditor": "Verichains",
      "auditStatus": 2,
      "reportUrl": "https://verichains.io?search=TomoChain+Token"
    },
    {
      "coinId": 2071,
      "auditor": "Verichains",
      "auditStatus": 2,
      "reportUrl": "https://verichains.io?search=Request+Network"
    },
    {
      "coinId": 3581,
      "auditor": "Verichains",
      "auditStatus": 2,
      "reportUrl": "https://verichains.io?search=Kleros+ICO"
    },
    {
      "coinId": 9148,
      "auditor": "Verichains",
      "auditStatus": 2,
      "reportUrl": "https://verichains.io?search=Drep"
    },
    {
      "coinId": 2840,
      "auditor": "Verichains",
      "auditStatus": 2,
      "reportUrl": "https://verichains.io?search=QuarkChain"
    },
    {
      "coinId": 8190,
      "auditor": "Verichains",
      "auditStatus": 2,
      "reportUrl": "https://verichains.io?search=BSCex+LaunchPoolX"
    },
    {
      "coinId": 9549,
      "auditor": "Verichains",
      "auditStatus": 2,
      "reportUrl": "https://verichains.io?search=Mercurial+Finance"
    },
    {
      "coinId": 9783,
      "auditor": "Verichains",
      "auditStatus": 2,
      "reportUrl": "https://verichains.io?search=Roseon+Finance+Token"
    },
    {
      "coinId": 10848,
      "auditor": "Verichains",
      "auditStatus": 2,
      "reportUrl": "https://verichains.io?search=Polyroll+Yield+Farm"
    },
    {
      "coinId": 11672,
      "auditor": "Verichains",
      "auditStatus": 2,
      "reportUrl": "https://verichains.io?search=Poco"
    },
    {
      "coinId": 11967,
      "auditor": "Verichains",
      "auditStatus": 2,
      "reportUrl": "https://verichains.io?search=Hero+Arena"
    },
    {
      "coinId": 13164,
      "auditor": "Verichains",
      "auditStatus": 2,
      "reportUrl": "https://verichains.io?search=HeroFi"
    },
    {
      "coinId": 11480,
      "auditor": "Verichains",
      "auditStatus": 2,
      "reportUrl": "https://verichains.io?search=LaunchZone+Token"
    },
    {
      "coinId": 12252,
      "auditor": "Verichains",
      "auditStatus": 2,
      "reportUrl": "https://verichains.io?search=BCoin+Token"
    },
    {
      "coinId": 12751,
      "auditor": "Verichains",
      "auditStatus": 2,
      "reportUrl": "https://verichains.io?search=Blockchain+Monster+Hunt"
    },
    {
      "coinId": 11926,
      "auditor": "Verichains",
      "auditStatus": 2,
      "reportUrl": "https://verichains.io?search=Thetan+Arena"
    },
    {
      "coinId": 18659,
      "auditor": "Verichains",
      "auditStatus": 2,
      "reportUrl": "https://verichains.io?search=Cyball"
    },
    {
      "coinId": 7216,
      "auditor": "Verichains",
      "auditStatus": 2,
      "reportUrl": "https://verichains.io?search=LuaSwap"
    },
    {
      "coinId": 11110,
      "auditor": "Verichains",
      "auditStatus": 2,
      "reportUrl": "https://verichains.io?search=Spores"
    },
    {
      "coinId": 13403,
      "auditor": "Verichains",
      "auditStatus": 2,
      "reportUrl": "https://verichains.io?search=Howl+City"
    },
    {
      "coinId": 34893,
      "auditor": "Verichains",
      "auditStatus": 2,
      "reportUrl": "https://verichains.io?search=gluteus+maximus"
    },
    {
      "coinId": 33494,
      "auditor": "Verichains",
      "auditStatus": 2,
      "reportUrl": "https://verichains.io?search=foru+ai"
    }
  ]
}
